aind_session/__init__.py
aind_session/extension.py
aind_session/py.typed
aind_session/session.py
aind_session/subject.py
aind_session/extensions/__init__.py
aind_session/extensions/ecephys.py
aind_session/extensions/lims.py
aind_session/extensions/smartspim_neuropixels.py
aind_session/utils/__init__.py
aind_session/utils/codeocean_utils.py
aind_session/utils/docdb_utils.py
aind_session/utils/misc_utils.py
aind_session/utils/s3_utils.py
aind_session-0.3.21.dist-info/licenses/LICENSE
aind_session-0.3.21.dist-info/METADATA
aind_session-0.3.21.dist-info/WHEEL
aind_session-0.3.21.dist-info/entry_points.txt
aind_session-0.3.21.dist-info/top_level.txt
aind_session-0.3.21.dist-info/RECORD
