Metadata-Version: 2.4
Name: aind-session
Version: 0.3.21
Summary: User-friendly tools for accessing paths, metadata and assets related to AIND sessions.
Author-email: Ben Hardcastle <ben.hardcastle@alleninstitue.org>
License: MIT
Project-URL: Repository, https://github.com/AllenNeuralDynamics/aind-session
Project-URL: Issues, https://github.com/AllenNeuralDynamics/aind-session/issues
Classifier: Development Status :: 3 - Alpha
Classifier: Programming Language :: Python :: 3
Classifier: Programming Language :: Python :: 3.9
Classifier: Programming Language :: Python :: 3.10
Classifier: Programming Language :: Python :: 3.11
Classifier: License :: OSI Approved :: MIT License
Classifier: Operating System :: Microsoft :: Windows
Classifier: Operating System :: POSIX :: Linux
Requires-Python: >=3.9
License-File: LICENSE
Requires-Dist: codeocean==0.12.0
Requires-Dist: npc-io>=0.1.30
Requires-Dist: npc-session>=0.1.39
Requires-Dist: aind-data-access-api[docdb]>=1.2.2
Requires-Dist: tzdata>=2024.2
Requires-Dist: aind-codeocean-pipeline-monitor>=0.5.2
Dynamic: license-file
